pranzo/__init__.py
pranzo/analyze/__init__.py
pranzo/analyze/accessor.py
pranzo/analyze/analyzer.py
pranzo/analyze/fields.py
pranzo/postprocess/__init__.py
pranzo/postprocess/antonpaar_reader.py
pranzo/postprocess/meta_reader.py
pranzo/postprocess/tamair_reader.py
scripts/__init__.py
scripts/save_exp_data.py
pranzo-0.1.1.dist-info/AUTHORS
pranzo-0.1.1.dist-info/LICENSE
pranzo-0.1.1.dist-info/METADATA
pranzo-0.1.1.dist-info/WHEEL
pranzo-0.1.1.dist-info/entry_points.txt
pranzo-0.1.1.dist-info/top_level.txt
pranzo-0.1.1.dist-info/RECORD
