Metadata-Version: 2.1
Name: pranzo
Version: 0.1.1
Summary: couple experimental calo and rheo data
License-File: LICENSE
License-File: AUTHORS
Requires-Dist: numpy
Requires-Dist: pandas
Requires-Dist: scipy
Requires-Dist: bamboost
Requires-Dist: matplotlib
Requires-Dist: tomli
Requires-Dist: h5py
